{
  "meta": {
    "timestamp": "2026-04-10T11:29:08",
    "n_modules": 60,
    "method": "SVD on connectivity matrix (1 - distance), ablate component 1",
    "source_files": [
      "operadic_dynamics_results.json",
      "gamma_wormhole_results.json"
    ]
  },
  "svd_components": {
    "explained_variance_pct": [
      52.73603303763782,
      6.891466439360026,
      4.513521785434988,
      2.348840029705724,
      1.9816349959939492,
      1.936625681518405,
      1.5825722622661156,
      1.5141304215187268,
      1.4671369935396101,
      1.4025273602785928
    ],
    "cumulative_variance_pct": [
      52.73603303763782,
      59.62749947699785,
      64.14102126243284,
      66.48986129213856,
      68.47149628813251,
      70.40812196965092,
      71.99069423191703,
      73.50482465343575,
      74.97196164697536,
      76.37448900725396
    ],
    "mode1_variance_pct": 52.73603303763782,
    "mode2_variance_pct": 6.891466439360026,
    "mode3_variance_pct": 4.513521785434988
  },
  "mode1_top_modules": [
    {
      "module": "error_functions",
      "loading": 0.18491882073092886
    },
    {
      "module": "multiple_zeta_values",
      "loading": 0.18415499114579048
    },
    {
      "module": "legendre_elliptic",
      "loading": 0.18397066138789195
    },
    {
      "module": "integer_sequences",
      "loading": 0.18356486453951187
    },
    {
      "module": "jacobi_theta",
      "loading": 0.18321589096024005
    },
    {
      "module": "carlson_elliptic",
      "loading": 0.17393269421500895
    },
    {
      "module": "chebyshev",
      "loading": 0.17083982405893222
    },
    {
      "module": "factorials",
      "loading": 0.16819264423514427
    },
    {
      "module": "beta_function",
      "loading": 0.16688706314734147
    },
    {
      "module": "fibonacci",
      "loading": 0.16636868388860818
    },
    {
      "module": "imaginary_unit",
      "loading": 0.16501473396432584
    },
    {
      "module": "agm",
      "loading": 0.1640679528494412
    },
    {
      "module": "golden_ratio",
      "loading": 0.1618738480084814
    },
    {
      "module": "modular_lambda",
      "loading": 0.16121679443584064
    },
    {
      "module": "pi",
      "loading": 0.15972514106038108
    },
    {
      "module": "modular_j",
      "loading": 0.15895886715187665
    },
    {
      "module": "dedekind_eta",
      "loading": 0.1523472967923812
    },
    {
      "module": "stirling_numbers",
      "loading": 0.15207187422940932
    },
    {
      "module": "confluent_hypergeometric",
      "loading": 0.14829169017995458
    },
    {
      "module": "eisenstein",
      "loading": 0.14795102901585327
    }
  ],
  "mode2_top_modules": [
    {
      "module": "integer_sequences",
      "loading": 0.2632196250000051
    },
    {
      "module": "coulomb_wave",
      "loading": -0.24305674347055975
    },
    {
      "module": "gauss_hypergeometric",
      "loading": -0.23264763702906108
    },
    {
      "module": "gaussian_quadrature",
      "loading": -0.22876110935500804
    },
    {
      "module": "beta_function",
      "loading": -0.22680252966533584
    },
    {
      "module": "imaginary_unit",
      "loading": 0.21198345499432428
    },
    {
      "module": "modular_lambda",
      "loading": 0.21016014945758735
    },
    {
      "module": "confluent_hypergeometric",
      "loading": -0.20923569845289394
    },
    {
      "module": "multiple_zeta_values",
      "loading": 0.2072512052153047
    },
    {
      "module": "golden_ratio",
      "loading": 0.19769708981241293
    },
    {
      "module": "stirling_numbers",
      "loading": -0.18736670086148122
    },
    {
      "module": "general_functions",
      "loading": -0.1858898783708964
    },
    {
      "module": "modular_j",
      "loading": 0.1843145815637016
    },
    {
      "module": "error_functions",
      "loading": 0.18279530157092902
    },
    {
      "module": "legendre_elliptic",
      "loading": 0.16907418295440357
    },
    {
      "module": "fibonacci",
      "loading": 0.16532447656638488
    },
    {
      "module": "pi",
      "loading": 0.16400827498355922
    },
    {
      "module": "modular_transformations",
      "loading": -0.1599463689789818
    },
    {
      "module": "powers",
      "loading": -0.1523696644984839
    },
    {
      "module": "bessel",
      "loading": -0.14682401005264392
    }
  ],
  "mode2_positive_pole": [
    {
      "module": "integer_sequences",
      "loading": 0.2632196250000051
    },
    {
      "module": "imaginary_unit",
      "loading": 0.21198345499432428
    },
    {
      "module": "modular_lambda",
      "loading": 0.21016014945758735
    },
    {
      "module": "multiple_zeta_values",
      "loading": 0.2072512052153047
    },
    {
      "module": "golden_ratio",
      "loading": 0.19769708981241293
    },
    {
      "module": "modular_j",
      "loading": 0.1843145815637016
    },
    {
      "module": "error_functions",
      "loading": 0.18279530157092902
    },
    {
      "module": "legendre_elliptic",
      "loading": 0.16907418295440357
    },
    {
      "module": "fibonacci",
      "loading": 0.16532447656638488
    },
    {
      "module": "pi",
      "loading": 0.16400827498355922
    }
  ],
  "mode2_negative_pole": [
    {
      "module": "coulomb_wave",
      "loading": -0.24305674347055975
    },
    {
      "module": "gauss_hypergeometric",
      "loading": -0.23264763702906108
    },
    {
      "module": "gaussian_quadrature",
      "loading": -0.22876110935500804
    },
    {
      "module": "beta_function",
      "loading": -0.22680252966533584
    },
    {
      "module": "confluent_hypergeometric",
      "loading": -0.20923569845289394
    },
    {
      "module": "stirling_numbers",
      "loading": -0.18736670086148122
    },
    {
      "module": "general_functions",
      "loading": -0.1858898783708964
    },
    {
      "module": "modular_transformations",
      "loading": -0.1599463689789818
    },
    {
      "module": "powers",
      "loading": -0.1523696644984839
    },
    {
      "module": "bessel",
      "loading": -0.14682401005264392
    }
  ],
  "mode3_top_modules": [
    {
      "module": "general_functions",
      "loading": 0.36593279511805993
    },
    {
      "module": "integrals",
      "loading": 0.3014828036212083
    },
    {
      "module": "operators",
      "loading": 0.2995068643078229
    },
    {
      "module": "const_catalan",
      "loading": 0.28048494111755834
    },
    {
      "module": "gaussian_quadrature",
      "loading": 0.27706331315925975
    },
    {
      "module": "const_gamma",
      "loading": 0.261629036552459
    },
    {
      "module": "bessel",
      "loading": -0.2252213316299747
    },
    {
      "module": "sinc",
      "loading": 0.22399823886843281
    },
    {
      "module": "halphen_constant",
      "loading": 0.20346712058202795
    },
    {
      "module": "powers",
      "loading": -0.19746198875054224
    },
    {
      "module": "pi",
      "loading": 0.1588811887425818
    },
    {
      "module": "gauss_hypergeometric",
      "loading": -0.14812113818920453
    },
    {
      "module": "complex_parts",
      "loading": -0.14724273463772583
    },
    {
      "module": "symbolic_expressions",
      "loading": 0.1427801644327418
    },
    {
      "module": "coulomb_wave",
      "loading": -0.14187033264190382
    },
    {
      "module": "gcd",
      "loading": -0.12291858462614652
    },
    {
      "module": "beta_function",
      "loading": -0.1136776462869084
    },
    {
      "module": "totient",
      "loading": 0.11145662546292115
    },
    {
      "module": "lambertw",
      "loading": -0.10337926661955578
    },
    {
      "module": "sqrt",
      "loading": -0.09556658555326561
    }
  ],
  "ablation_gains_top30": [
    {
      "module_a": "error_functions",
      "module_b": "symbolic_expressions",
      "original_connectivity": 0.019000000000000017,
      "ablated_connectivity": 0.15738873483817659,
      "delta": 0.13838873483817657,
      "original_distance": 0.981
    },
    {
      "module_a": "multiple_zeta_values",
      "module_b": "symbolic_expressions",
      "original_connectivity": 0.02849999999999997,
      "ablated_connectivity": 0.1663171034082256,
      "delta": 0.13781710340822562,
      "original_distance": 0.9715
    },
    {
      "module_a": "legendre_elliptic",
      "module_b": "symbolic_expressions",
      "original_connectivity": 0.012199999999999989,
      "ablated_connectivity": 0.14987915551364256,
      "delta": 0.13767915551364257,
      "original_distance": 0.9878
    },
    {
      "module_a": "integer_sequences",
      "module_b": "symbolic_expressions",
      "original_connectivity": 0.019100000000000006,
      "ablated_connectivity": 0.15647546705063664,
      "delta": 0.13737546705063663,
      "original_distance": 0.9809
    },
    {
      "module_a": "jacobi_theta",
      "module_b": "symbolic_expressions",
      "original_connectivity": 0.02729999999999999,
      "ablated_connectivity": 0.1644143037361807,
      "delta": 0.13711430373618072,
      "original_distance": 0.9727
    },
    {
      "module_a": "carlson_elliptic",
      "module_b": "symbolic_expressions",
      "original_connectivity": 0.01090000000000002,
      "ablated_connectivity": 0.1410669857306451,
      "delta": 0.13016698573064509,
      "original_distance": 0.9891
    },
    {
      "module_a": "chebyshev",
      "module_b": "symbolic_expressions",
      "original_connectivity": 0.023399999999999976,
      "ablated_connectivity": 0.15125235714807905,
      "delta": 0.12785235714807908,
      "original_distance": 0.9766
    },
    {
      "module_a": "factorials",
      "module_b": "symbolic_expressions",
      "original_connectivity": 0.02429999999999999,
      "ablated_connectivity": 0.15017127233878194,
      "delta": 0.12587127233878195,
      "original_distance": 0.9757
    },
    {
      "module_a": "beta_function",
      "module_b": "symbolic_expressions",
      "original_connectivity": 0.023499999999999965,
      "ablated_connectivity": 0.14839420729880645,
      "delta": 0.12489420729880649,
      "original_distance": 0.9765
    },
    {
      "module_a": "fibonacci",
      "module_b": "symbolic_expressions",
      "original_connectivity": 0.02300000000000002,
      "ablated_connectivity": 0.14750626490603713,
      "delta": 0.12450626490603711,
      "original_distance": 0.977
    },
    {
      "module_a": "imaginary_unit",
      "module_b": "symbolic_expressions",
      "original_connectivity": 0.011600000000000055,
      "ablated_connectivity": 0.13509300180866807,
      "delta": 0.12349300180866801,
      "original_distance": 0.9884
    },
    {
      "module_a": "agm",
      "module_b": "symbolic_expressions",
      "original_connectivity": 0.015900000000000025,
      "ablated_connectivity": 0.13868445391646506,
      "delta": 0.12278445391646503,
      "original_distance": 0.9841
    },
    {
      "module_a": "golden_ratio",
      "module_b": "symbolic_expressions",
      "original_connectivity": 0.01859999999999995,
      "ablated_connectivity": 0.13974243937277187,
      "delta": 0.12114243937277192,
      "original_distance": 0.9814
    },
    {
      "module_a": "error_functions",
      "module_b": "prime_numbers",
      "original_connectivity": 0.022199999999999998,
      "ablated_connectivity": 0.14306979044207896,
      "delta": 0.12086979044207896,
      "original_distance": 0.9778
    },
    {
      "module_a": "modular_lambda",
      "module_b": "symbolic_expressions",
      "original_connectivity": 0.023499999999999965,
      "ablated_connectivity": 0.14415071650606082,
      "delta": 0.12065071650606085,
      "original_distance": 0.9765
    },
    {
      "module_a": "multiple_zeta_values",
      "module_b": "prime_numbers",
      "original_connectivity": 0.023299999999999987,
      "ablated_connectivity": 0.14367052313373144,
      "delta": 0.12037052313373145,
      "original_distance": 0.9767
    },
    {
      "module_a": "legendre_elliptic",
      "module_b": "prime_numbers",
      "original_connectivity": 0.026000000000000023,
      "ablated_connectivity": 0.1462500383765749,
      "delta": 0.12025003837657489,
      "original_distance": 0.974
    },
    {
      "module_a": "integer_sequences",
      "module_b": "prime_numbers",
      "original_connectivity": 0.03280000000000005,
      "ablated_connectivity": 0.15278479452615515,
      "delta": 0.1199847945261551,
      "original_distance": 0.9672
    },
    {
      "module_a": "jacobi_theta",
      "module_b": "prime_numbers",
      "original_connectivity": 0.031100000000000017,
      "ablated_connectivity": 0.15085669246910285,
      "delta": 0.11975669246910284,
      "original_distance": 0.9689
    },
    {
      "module_a": "pi",
      "module_b": "symbolic_expressions",
      "original_connectivity": 0.036800000000000055,
      "ablated_connectivity": 0.15633439950473574,
      "delta": 0.11953439950473568,
      "original_distance": 0.9632
    },
    {
      "module_a": "modular_j",
      "module_b": "symbolic_expressions",
      "original_connectivity": 0.01649999999999996,
      "ablated_connectivity": 0.1354609388028001,
      "delta": 0.11896093880280015,
      "original_distance": 0.9835
    },
    {
      "module_a": "error_functions",
      "module_b": "logic",
      "original_connectivity": 0.015199999999999991,
      "ablated_connectivity": 0.13285641718935134,
      "delta": 0.11765641718935135,
      "original_distance": 0.9848
    },
    {
      "module_a": "legendre_elliptic",
      "module_b": "logic",
      "original_connectivity": 0.009399999999999964,
      "ablated_connectivity": 0.12645314148823356,
      "delta": 0.11705314148823359,
      "original_distance": 0.9906
    },
    {
      "module_a": "integer_sequences",
      "module_b": "logic",
      "original_connectivity": 0.025399999999999978,
      "ablated_connectivity": 0.1421949492550233,
      "delta": 0.11679494925502332,
      "original_distance": 0.9746
    },
    {
      "module_a": "jacobi_theta",
      "module_b": "logic",
      "original_connectivity": 0.023599999999999954,
      "ablated_connectivity": 0.14017291138527813,
      "delta": 0.11657291138527817,
      "original_distance": 0.9764
    },
    {
      "module_a": "error_functions",
      "module_b": "numbers",
      "original_connectivity": 0.02629999999999999,
      "ablated_connectivity": 0.14131835745594246,
      "delta": 0.11501835745594247,
      "original_distance": 0.9737
    },
    {
      "module_a": "multiple_zeta_values",
      "module_b": "numbers",
      "original_connectivity": 0.030200000000000005,
      "ablated_connectivity": 0.14474326020022993,
      "delta": 0.11454326020022992,
      "original_distance": 0.9698
    },
    {
      "module_a": "legendre_elliptic",
      "module_b": "numbers",
      "original_connectivity": 0.026000000000000023,
      "ablated_connectivity": 0.1404286082361954,
      "delta": 0.11442860823619538,
      "original_distance": 0.974
    },
    {
      "module_a": "integer_sequences",
      "module_b": "numbers",
      "original_connectivity": 0.03990000000000005,
      "ablated_connectivity": 0.15407620511802186,
      "delta": 0.11417620511802182,
      "original_distance": 0.9601
    },
    {
      "module_a": "dedekind_eta",
      "module_b": "symbolic_expressions",
      "original_connectivity": 0.023800000000000043,
      "ablated_connectivity": 0.13781300081721515,
      "delta": 0.1140130008172151,
      "original_distance": 0.9762
    }
  ],
  "ablation_losses_top30": [
    {
      "module_a": "beta_function",
      "module_b": "multiple_zeta_values",
      "original_connectivity": 0.1502,
      "ablated_connectivity": 0.10528015275283009,
      "delta": -0.04491984724716991,
      "original_distance": 0.8498
    },
    {
      "module_a": "bernoulli_numbers",
      "module_b": "jacobi_theta",
      "original_connectivity": 0.1653,
      "ablated_connectivity": 0.12011431943156169,
      "delta": -0.045185680568438316,
      "original_distance": 0.8347
    },
    {
      "module_a": "factorials",
      "module_b": "multiple_zeta_values",
      "original_connectivity": 0.19289999999999996,
      "ablated_connectivity": 0.14762873843750293,
      "delta": -0.04527126156249703,
      "original_distance": 0.8071
    },
    {
      "module_a": "agm",
      "module_b": "chebyshev",
      "original_connectivity": 0.18969999999999998,
      "ablated_connectivity": 0.14439243322454787,
      "delta": -0.04530756677545211,
      "original_distance": 0.8103
    },
    {
      "module_a": "chebyshev",
      "module_b": "multiple_zeta_values",
      "original_connectivity": 0.17610000000000003,
      "ablated_connectivity": 0.13011621518328662,
      "delta": -0.04598378481671342,
      "original_distance": 0.8239
    },
    {
      "module_a": "beta_function",
      "module_b": "chebyshev",
      "original_connectivity": 0.22809999999999997,
      "ablated_connectivity": 0.18201393245184247,
      "delta": -0.0460860675481575,
      "original_distance": 0.7719
    },
    {
      "module_a": "hurwitz_zeta",
      "module_b": "jacobi_theta",
      "original_connectivity": 0.16900000000000004,
      "ablated_connectivity": 0.12269377064970295,
      "delta": -0.04630622935029709,
      "original_distance": 0.831
    },
    {
      "module_a": "carlson_elliptic",
      "module_b": "multiple_zeta_values",
      "original_connectivity": 0.20030000000000003,
      "ablated_connectivity": 0.15348372851627864,
      "delta": -0.04681627148372139,
      "original_distance": 0.7997
    },
    {
      "module_a": "digamma_function",
      "module_b": "jacobi_theta",
      "original_connectivity": 0.18220000000000003,
      "ablated_connectivity": 0.1350162804983449,
      "delta": -0.04718371950165512,
      "original_distance": 0.8178
    },
    {
      "module_a": "carlson_elliptic",
      "module_b": "chebyshev",
      "original_connectivity": 0.17410000000000003,
      "ablated_connectivity": 0.12606827277529084,
      "delta": -0.04803172722470919,
      "original_distance": 0.8259
    },
    {
      "module_a": "gauss_hypergeometric",
      "module_b": "jacobi_theta",
      "original_connectivity": 0.21120000000000005,
      "ablated_connectivity": 0.16314121638155268,
      "delta": -0.04805878361844737,
      "original_distance": 0.7888
    },
    {
      "module_a": "const_catalan",
      "module_b": "jacobi_theta",
      "original_connectivity": 0.18730000000000002,
      "ablated_connectivity": 0.1389465678513796,
      "delta": -0.04835343214862042,
      "original_distance": 0.8127
    },
    {
      "module_a": "gcd",
      "module_b": "jacobi_theta",
      "original_connectivity": 0.1965,
      "ablated_connectivity": 0.14753966678105776,
      "delta": -0.04896033321894225,
      "original_distance": 0.8035
    },
    {
      "module_a": "jacobi_theta",
      "module_b": "multiple_zeta_values",
      "original_connectivity": 0.22519999999999996,
      "ablated_connectivity": 0.17588503405849998,
      "delta": -0.04931496594149998,
      "original_distance": 0.7748
    },
    {
      "module_a": "integer_sequences",
      "module_b": "multiple_zeta_values",
      "original_connectivity": 0.249,
      "ablated_connectivity": 0.19959110323139723,
      "delta": -0.04940889676860277,
      "original_distance": 0.751
    },
    {
      "module_a": "legendre_elliptic",
      "module_b": "multiple_zeta_values",
      "original_connectivity": 0.2218,
      "ablated_connectivity": 0.17228187767431186,
      "delta": -0.04951812232568814,
      "original_distance": 0.7782
    },
    {
      "module_a": "eisenstein",
      "module_b": "jacobi_theta",
      "original_connectivity": 0.20230000000000004,
      "ablated_connectivity": 0.1527286530846818,
      "delta": -0.049571346915318226,
      "original_distance": 0.7977
    },
    {
      "module_a": "confluent_hypergeometric",
      "module_b": "jacobi_theta",
      "original_connectivity": 0.19920000000000004,
      "ablated_connectivity": 0.14951451374507346,
      "delta": -0.04968548625492658,
      "original_distance": 0.8008
    },
    {
      "module_a": "error_functions",
      "module_b": "multiple_zeta_values",
      "original_connectivity": 0.2126,
      "ablated_connectivity": 0.16282666812090513,
      "delta": -0.049773331879094884,
      "original_distance": 0.7874
    },
    {
      "module_a": "dedekind_eta",
      "module_b": "jacobi_theta",
      "original_connectivity": 0.18230000000000002,
      "ablated_connectivity": 0.13125567302815544,
      "delta": -0.05104432697184458,
      "original_distance": 0.8177
    },
    {
      "module_a": "golden_ratio",
      "module_b": "jacobi_theta",
      "original_connectivity": 0.19789999999999996,
      "ablated_connectivity": 0.14366377920773962,
      "delta": -0.05423622079226034,
      "original_distance": 0.8021
    },
    {
      "module_a": "agm",
      "module_b": "jacobi_theta",
      "original_connectivity": 0.20220000000000005,
      "ablated_connectivity": 0.14722863912143355,
      "delta": -0.054971360878566494,
      "original_distance": 0.7978
    },
    {
      "module_a": "imaginary_unit",
      "module_b": "jacobi_theta",
      "original_connectivity": 0.17559999999999998,
      "ablated_connectivity": 0.1203114178394255,
      "delta": -0.05528858216057447,
      "original_distance": 0.8244
    },
    {
      "module_a": "fibonacci",
      "module_b": "jacobi_theta",
      "original_connectivity": 0.20540000000000003,
      "ablated_connectivity": 0.1496577736718315,
      "delta": -0.055742226328168526,
      "original_distance": 0.7946
    },
    {
      "module_a": "beta_function",
      "module_b": "jacobi_theta",
      "original_connectivity": 0.2229,
      "ablated_connectivity": 0.16698408945862053,
      "delta": -0.055915910541379454,
      "original_distance": 0.7771
    },
    {
      "module_a": "factorials",
      "module_b": "jacobi_theta",
      "original_connectivity": 0.2168,
      "ablated_connectivity": 0.16044665138563075,
      "delta": -0.05635334861436925,
      "original_distance": 0.7832
    },
    {
      "module_a": "chebyshev",
      "module_b": "jacobi_theta",
      "original_connectivity": 0.21940000000000004,
      "ablated_connectivity": 0.16215970744029212,
      "delta": -0.05724029255970792,
      "original_distance": 0.7806
    },
    {
      "module_a": "carlson_elliptic",
      "module_b": "jacobi_theta",
      "original_connectivity": 0.19489999999999996,
      "ablated_connectivity": 0.13662343388078554,
      "delta": -0.05827656611921442,
      "original_distance": 0.8051
    },
    {
      "module_a": "integer_sequences",
      "module_b": "jacobi_theta",
      "original_connectivity": 0.19340000000000002,
      "ablated_connectivity": 0.13189615212492706,
      "delta": -0.06150384787507296,
      "original_distance": 0.8066
    },
    {
      "module_a": "error_functions",
      "module_b": "jacobi_theta",
      "original_connectivity": 0.2067,
      "ablated_connectivity": 0.1447425058575146,
      "delta": -0.061957494142485386,
      "original_distance": 0.7933
    }
  ],
  "mode2_loadbearing_symbols": [
    {
      "symbol": "Recurrence",
      "centrality_gain": 0.036599447823364994,
      "mode2_load": 0.006195764768678944,
      "combined_score": 0.0002267615693771081,
      "n_module_pairs": 1,
      "is_universal_operator": false,
      "is_universal_companion": false
    },
    {
      "symbol": "NotEqual",
      "centrality_gain": 0.01517170799164036,
      "mode2_load": 0.009418342658196173,
      "combined_score": 0.00014289234457536218,
      "n_module_pairs": 1,
      "is_universal_operator": false,
      "is_universal_companion": false
    },
    {
      "symbol": "Entries",
      "centrality_gain": 0.010879122559452364,
      "mode2_load": 0.006609000506849761,
      "combined_score": 7.190012650950135e-05,
      "n_module_pairs": 1,
      "is_universal_operator": false,
      "is_universal_companion": false
    },
    {
      "symbol": "Section",
      "centrality_gain": 0.010879122559452364,
      "mode2_load": 0.006609000506849761,
      "combined_score": 7.190012650950135e-05,
      "n_module_pairs": 1,
      "is_universal_operator": false,
      "is_universal_companion": false
    },
    {
      "symbol": "SeeTopics",
      "centrality_gain": 0.010879122559452364,
      "mode2_load": 0.006609000506849761,
      "combined_score": 7.190012650950135e-05,
      "n_module_pairs": 1,
      "is_universal_operator": false,
      "is_universal_companion": false
    },
    {
      "symbol": "Title",
      "centrality_gain": 0.010879122559452364,
      "mode2_load": 0.006609000506849761,
      "combined_score": 7.190012650950135e-05,
      "n_module_pairs": 1,
      "is_universal_operator": false,
      "is_universal_companion": false
    },
    {
      "symbol": "PowerSeries",
      "centrality_gain": 0.021995331754130126,
      "mode2_load": 0.00252695073697687,
      "combined_score": 5.558111978614988e-05,
      "n_module_pairs": 1,
      "is_universal_operator": false,
      "is_universal_companion": false
    },
    {
      "symbol": "Sin",
      "centrality_gain": 0.006119167899849641,
      "mode2_load": 0.007949842674605318,
      "combined_score": 4.8646422103299675e-05,
      "n_module_pairs": 10,
      "is_universal_operator": false,
      "is_universal_companion": false
    },
    {
      "symbol": "Decimal",
      "centrality_gain": 0.012691783082195818,
      "mode2_load": 0.003437221123155007,
      "combined_score": 4.362446490062482e-05,
      "n_module_pairs": 10,
      "is_universal_operator": false,
      "is_universal_companion": false
    },
    {
      "symbol": "NearestDecimal",
      "centrality_gain": 0.012691783082195818,
      "mode2_load": 0.003437221123155007,
      "combined_score": 4.362446490062482e-05,
      "n_module_pairs": 10,
      "is_universal_operator": false,
      "is_universal_companion": false
    },
    {
      "symbol": "TableSplit",
      "centrality_gain": 0.012691783082195818,
      "mode2_load": 0.003437221123155007,
      "combined_score": 4.362446490062482e-05,
      "n_module_pairs": 10,
      "is_universal_operator": false,
      "is_universal_companion": false
    },
    {
      "symbol": "TableValueHeadings",
      "centrality_gain": 0.012691783082195818,
      "mode2_load": 0.003437221123155007,
      "combined_score": 4.362446490062482e-05,
      "n_module_pairs": 10,
      "is_universal_operator": false,
      "is_universal_companion": false
    },
    {
      "symbol": "Var",
      "centrality_gain": 0.012691783082195818,
      "mode2_load": 0.003437221123155007,
      "combined_score": 4.362446490062482e-05,
      "n_module_pairs": 10,
      "is_universal_operator": false,
      "is_universal_companion": false
    },
    {
      "symbol": "GreaterEqual",
      "centrality_gain": 0.017795036550106752,
      "mode2_load": 0.002228518660398786,
      "combined_score": 3.965657101439134e-05,
      "n_module_pairs": 1,
      "is_universal_operator": false,
      "is_universal_companion": false
    },
    {
      "symbol": "LessEqual",
      "centrality_gain": 0.00886548197792047,
      "mode2_load": 0.0040341000170246695,
      "combined_score": 3.576424099806087e-05,
      "n_module_pairs": 36,
      "is_universal_operator": false,
      "is_universal_companion": false
    },
    {
      "symbol": "BernoulliB",
      "centrality_gain": 0.009918832467290278,
      "mode2_load": 0.0032350919628314377,
      "combined_score": 3.20883351956023e-05,
      "n_module_pairs": 1,
      "is_universal_operator": false,
      "is_universal_companion": false
    },
    {
      "symbol": "Series",
      "centrality_gain": 0.009918832467290278,
      "mode2_load": 0.0032350919628314377,
      "combined_score": 3.20883351956023e-05,
      "n_module_pairs": 1,
      "is_universal_operator": false,
      "is_universal_companion": false
    },
    {
      "symbol": "ConstE",
      "centrality_gain": 0.015723836619241205,
      "mode2_load": 0.001764789045386156,
      "combined_score": 2.774925461707857e-05,
      "n_module_pairs": 1,
      "is_universal_operator": false,
      "is_universal_companion": false
    },
    {
      "symbol": "Representation",
      "centrality_gain": 0.014407781189171659,
      "mode2_load": 0.0018237821299645549,
      "combined_score": 2.6276653865250735e-05,
      "n_module_pairs": 1,
      "is_universal_operator": false,
      "is_universal_companion": false
    },
    {
      "symbol": "Cos",
      "centrality_gain": 0.007184252163034288,
      "mode2_load": 0.002943046637066649,
      "combined_score": 2.114358916825686e-05,
      "n_module_pairs": 10,
      "is_universal_operator": false,
      "is_universal_companion": false
    },
    {
      "symbol": "Product",
      "centrality_gain": 0.006373625080024194,
      "mode2_load": 0.0023342698956224195,
      "combined_score": 1.4877761150284509e-05,
      "n_module_pairs": 3,
      "is_universal_operator": false,
      "is_universal_companion": false
    },
    {
      "symbol": "ConstGamma",
      "centrality_gain": 0.006546704631506815,
      "mode2_load": 0.0018606622863653643,
      "combined_score": 1.2181206407818191e-05,
      "n_module_pairs": 3,
      "is_universal_operator": false,
      "is_universal_companion": false
    },
    {
      "symbol": "RiemannZeta",
      "centrality_gain": 0.0045941674873690415,
      "mode2_load": 0.002098088872203604,
      "combined_score": 9.638971682288579e-06,
      "n_module_pairs": 6,
      "is_universal_operator": false,
      "is_universal_companion": false
    },
    {
      "symbol": "ZZLessEqual",
      "centrality_gain": 0.0009263845116510458,
      "mode2_load": 0.004801379220644221,
      "combined_score": 4.447923344567976e-06,
      "n_module_pairs": 28,
      "is_universal_operator": false,
      "is_universal_companion": true
    },
    {
      "symbol": "DivisorSum",
      "centrality_gain": 0.0007587563237414219,
      "mode2_load": 0.0011263499199275185,
      "combined_score": 8.546251244906488e-07,
      "n_module_pairs": 1,
      "is_universal_operator": false,
      "is_universal_companion": false
    },
    {
      "symbol": "GCD",
      "centrality_gain": 0.0007587563237414219,
      "mode2_load": 0.0011263499199275185,
      "combined_score": 8.546251244906488e-07,
      "n_module_pairs": 1,
      "is_universal_operator": false,
      "is_universal_companion": false
    },
    {
      "symbol": "Totient",
      "centrality_gain": 0.0007587563237414219,
      "mode2_load": 0.0011263499199275185,
      "combined_score": 8.546251244906488e-07,
      "n_module_pairs": 1,
      "is_universal_operator": false,
      "is_universal_companion": false
    },
    {
      "symbol": "Derivatives",
      "centrality_gain": -0.00025919310874646567,
      "mode2_load": 0.0051233605003018975,
      "combined_score": -1.3279397353020965e-06,
      "n_module_pairs": 3,
      "is_universal_operator": false,
      "is_universal_companion": false
    },
    {
      "symbol": "Sinc",
      "centrality_gain": -0.003689424219886467,
      "mode2_load": 0.00078705704523814,
      "combined_score": -2.9037873251338724e-06,
      "n_module_pairs": 1,
      "is_universal_operator": false,
      "is_universal_companion": false
    },
    {
      "symbol": "PolyLog",
      "centrality_gain": -0.005561113323878153,
      "mode2_load": 0.0010252927587900609,
      "combined_score": -5.7017692217831966e-06,
      "n_module_pairs": 1,
      "is_universal_operator": false,
      "is_universal_companion": false
    }
  ],
  "symbol_centrality_gainers": [
    {
      "symbol": "Recurrence",
      "avg_delta": 0.036599447823364994,
      "n_pairs": 1,
      "is_universal": false
    },
    {
      "symbol": "PowerSeries",
      "avg_delta": 0.021995331754130126,
      "n_pairs": 1,
      "is_universal": false
    },
    {
      "symbol": "GreaterEqual",
      "avg_delta": 0.017795036550106752,
      "n_pairs": 1,
      "is_universal": false
    },
    {
      "symbol": "ConstE",
      "avg_delta": 0.015723836619241205,
      "n_pairs": 1,
      "is_universal": false
    },
    {
      "symbol": "NotEqual",
      "avg_delta": 0.01517170799164036,
      "n_pairs": 1,
      "is_universal": false
    },
    {
      "symbol": "Representation",
      "avg_delta": 0.014407781189171659,
      "n_pairs": 1,
      "is_universal": false
    },
    {
      "symbol": "Decimal",
      "avg_delta": 0.012691783082195818,
      "n_pairs": 10,
      "is_universal": false
    },
    {
      "symbol": "NearestDecimal",
      "avg_delta": 0.012691783082195818,
      "n_pairs": 10,
      "is_universal": false
    },
    {
      "symbol": "TableSplit",
      "avg_delta": 0.012691783082195818,
      "n_pairs": 10,
      "is_universal": false
    },
    {
      "symbol": "TableValueHeadings",
      "avg_delta": 0.012691783082195818,
      "n_pairs": 10,
      "is_universal": false
    },
    {
      "symbol": "Var",
      "avg_delta": 0.012691783082195818,
      "n_pairs": 10,
      "is_universal": false
    },
    {
      "symbol": "Entries",
      "avg_delta": 0.010879122559452364,
      "n_pairs": 1,
      "is_universal": false
    },
    {
      "symbol": "Section",
      "avg_delta": 0.010879122559452364,
      "n_pairs": 1,
      "is_universal": false
    },
    {
      "symbol": "SeeTopics",
      "avg_delta": 0.010879122559452364,
      "n_pairs": 1,
      "is_universal": false
    },
    {
      "symbol": "Title",
      "avg_delta": 0.010879122559452364,
      "n_pairs": 1,
      "is_universal": false
    },
    {
      "symbol": "BernoulliB",
      "avg_delta": 0.009918832467290278,
      "n_pairs": 1,
      "is_universal": false
    },
    {
      "symbol": "Series",
      "avg_delta": 0.009918832467290278,
      "n_pairs": 1,
      "is_universal": false
    },
    {
      "symbol": "LessEqual",
      "avg_delta": 0.00886548197792047,
      "n_pairs": 36,
      "is_universal": false
    },
    {
      "symbol": "Cos",
      "avg_delta": 0.007184252163034288,
      "n_pairs": 10,
      "is_universal": false
    },
    {
      "symbol": "ConstGamma",
      "avg_delta": 0.006546704631506815,
      "n_pairs": 3,
      "is_universal": false
    },
    {
      "symbol": "Product",
      "avg_delta": 0.006373625080024194,
      "n_pairs": 3,
      "is_universal": false
    },
    {
      "symbol": "Sin",
      "avg_delta": 0.006119167899849641,
      "n_pairs": 10,
      "is_universal": false
    },
    {
      "symbol": "RiemannZeta",
      "avg_delta": 0.0045941674873690415,
      "n_pairs": 6,
      "is_universal": false
    },
    {
      "symbol": "ZZLessEqual",
      "avg_delta": 0.0009263845116510458,
      "n_pairs": 28,
      "is_universal": true
    },
    {
      "symbol": "DivisorSum",
      "avg_delta": 0.0007587563237414219,
      "n_pairs": 1,
      "is_universal": false
    },
    {
      "symbol": "GCD",
      "avg_delta": 0.0007587563237414219,
      "n_pairs": 1,
      "is_universal": false
    },
    {
      "symbol": "Totient",
      "avg_delta": 0.0007587563237414219,
      "n_pairs": 1,
      "is_universal": false
    },
    {
      "symbol": "Derivatives",
      "avg_delta": -0.00025919310874646567,
      "n_pairs": 3,
      "is_universal": false
    },
    {
      "symbol": "Set",
      "avg_delta": -0.000596019526806546,
      "n_pairs": 1,
      "is_universal": true
    },
    {
      "symbol": "And",
      "avg_delta": -0.0012574294064465405,
      "n_pairs": 28,
      "is_universal": true
    }
  ],
  "symbol_centrality_losers": [
    {
      "symbol": "BellNumber",
      "avg_delta": -0.013332786735173796,
      "n_pairs": 1,
      "is_universal": false
    },
    {
      "symbol": "Im",
      "avg_delta": -0.014903783076043592,
      "n_pairs": 3,
      "is_universal": false
    },
    {
      "symbol": "Integral",
      "avg_delta": -0.014916433772980433,
      "n_pairs": 28,
      "is_universal": true
    },
    {
      "symbol": "Infinity",
      "avg_delta": -0.015148571579508826,
      "n_pairs": 66,
      "is_universal": true
    },
    {
      "symbol": "ConstI",
      "avg_delta": -0.015579129099402553,
      "n_pairs": 105,
      "is_universal": true
    },
    {
      "symbol": "Atan",
      "avg_delta": -0.017179353175392514,
      "n_pairs": 1,
      "is_universal": false
    },
    {
      "symbol": "Re",
      "avg_delta": -0.02003109985604692,
      "n_pairs": 15,
      "is_universal": true
    },
    {
      "symbol": "Sqrt",
      "avg_delta": -0.022239314659794587,
      "n_pairs": 45,
      "is_universal": true
    },
    {
      "symbol": "Greater",
      "avg_delta": -0.022852449878895616,
      "n_pairs": 15,
      "is_universal": true
    },
    {
      "symbol": "DedekindEta",
      "avg_delta": -0.025198404307817335,
      "n_pairs": 1,
      "is_universal": false
    },
    {
      "symbol": "EisensteinE",
      "avg_delta": -0.025198404307817335,
      "n_pairs": 1,
      "is_universal": false
    },
    {
      "symbol": "EisensteinG",
      "avg_delta": -0.025910309533551418,
      "n_pairs": 1,
      "is_universal": false
    },
    {
      "symbol": "JacobiTheta",
      "avg_delta": -0.03218784659119842,
      "n_pairs": 3,
      "is_universal": false
    },
    {
      "symbol": "Add",
      "avg_delta": -0.03267893817445713,
      "n_pairs": 3,
      "is_universal": false
    },
    {
      "symbol": "Mul",
      "avg_delta": -0.03267893817445713,
      "n_pairs": 3,
      "is_universal": false
    },
    {
      "symbol": "EllipticK",
      "avg_delta": -0.03287177886020128,
      "n_pairs": 3,
      "is_universal": false
    },
    {
      "symbol": "Sub",
      "avg_delta": -0.03389840492805013,
      "n_pairs": 1,
      "is_universal": false
    },
    {
      "symbol": "CarlsonRF",
      "avg_delta": -0.03593657869393707,
      "n_pairs": 1,
      "is_universal": false
    },
    {
      "symbol": "HH",
      "avg_delta": -0.0369105209911012,
      "n_pairs": 6,
      "is_universal": false
    },
    {
      "symbol": "Pow",
      "avg_delta": -0.03751245258656764,
      "n_pairs": 10,
      "is_universal": true
    }
  ],
  "module_degree_shift": [
    {
      "module": "jacobi_theta",
      "original_degree": 40,
      "ablated_degree": 54,
      "delta": 14
    },
    {
      "module": "beta_function",
      "original_degree": 25,
      "ablated_degree": 33,
      "delta": 8
    },
    {
      "module": "fibonacci",
      "original_degree": 27,
      "ablated_degree": 35,
      "delta": 8
    },
    {
      "module": "chebyshev",
      "original_degree": 37,
      "ablated_degree": 44,
      "delta": 7
    },
    {
      "module": "modular_lambda",
      "original_degree": 22,
      "ablated_degree": 28,
      "delta": 6
    },
    {
      "module": "complex_plane",
      "original_degree": 4,
      "ablated_degree": 9,
      "delta": 5
    },
    {
      "module": "legendre_polynomial",
      "original_degree": 28,
      "ablated_degree": 33,
      "delta": 5
    },
    {
      "module": "integer_sequences",
      "original_degree": 26,
      "ablated_degree": 30,
      "delta": 4
    },
    {
      "module": "legendre_elliptic",
      "original_degree": 24,
      "ablated_degree": 28,
      "delta": 4
    },
    {
      "module": "gauss_hypergeometric",
      "original_degree": 23,
      "ablated_degree": 26,
      "delta": 3
    },
    {
      "module": "general_functions",
      "original_degree": 9,
      "ablated_degree": 12,
      "delta": 3
    },
    {
      "module": "multiple_zeta_values",
      "original_degree": 28,
      "ablated_degree": 31,
      "delta": 3
    },
    {
      "module": "pi",
      "original_degree": 24,
      "ablated_degree": 27,
      "delta": 3
    },
    {
      "module": "error_functions",
      "original_degree": 24,
      "ablated_degree": 26,
      "delta": 2
    },
    {
      "module": "gcd",
      "original_degree": 22,
      "ablated_degree": 24,
      "delta": 2
    },
    {
      "module": "halphen_constant",
      "original_degree": 2,
      "ablated_degree": 4,
      "delta": 2
    },
    {
      "module": "integrals",
      "original_degree": 24,
      "ablated_degree": 26,
      "delta": 2
    },
    {
      "module": "stirling_numbers",
      "original_degree": 30,
      "ablated_degree": 32,
      "delta": 2
    },
    {
      "module": "gaussian_quadrature",
      "original_degree": 26,
      "ablated_degree": 27,
      "delta": 1
    },
    {
      "module": "lambertw",
      "original_degree": 2,
      "ablated_degree": 3,
      "delta": 1
    },
    {
      "module": "log",
      "original_degree": 3,
      "ablated_degree": 4,
      "delta": 1
    },
    {
      "module": "atan",
      "original_degree": 0,
      "ablated_degree": 0,
      "delta": 0
    },
    {
      "module": "bell_numbers",
      "original_degree": 0,
      "ablated_degree": 0,
      "delta": 0
    },
    {
      "module": "complex_parts",
      "original_degree": 1,
      "ablated_degree": 1,
      "delta": 0
    },
    {
      "module": "confluent_hypergeometric",
      "original_degree": 22,
      "ablated_degree": 22,
      "delta": 0
    },
    {
      "module": "const_catalan",
      "original_degree": 20,
      "ablated_degree": 20,
      "delta": 0
    },
    {
      "module": "eisenstein",
      "original_degree": 26,
      "ablated_degree": 26,
      "delta": 0
    },
    {
      "module": "gamma",
      "original_degree": 1,
      "ablated_degree": 1,
      "delta": 0
    },
    {
      "module": "landau_function",
      "original_degree": 0,
      "ablated_degree": 0,
      "delta": 0
    },
    {
      "module": "modular_j",
      "original_degree": 19,
      "ablated_degree": 19,
      "delta": 0
    },
    {
      "module": "numbers",
      "original_degree": 0,
      "ablated_degree": 0,
      "delta": 0
    },
    {
      "module": "operators",
      "original_degree": 4,
      "ablated_degree": 4,
      "delta": 0
    },
    {
      "module": "partitions",
      "original_degree": 0,
      "ablated_degree": 0,
      "delta": 0
    },
    {
      "module": "powers",
      "original_degree": 14,
      "ablated_degree": 14,
      "delta": 0
    },
    {
      "module": "prime_numbers",
      "original_degree": 0,
      "ablated_degree": 0,
      "delta": 0
    },
    {
      "module": "riemann_zeta",
      "original_degree": 0,
      "ablated_degree": 0,
      "delta": 0
    },
    {
      "module": "symbolic_expressions",
      "original_degree": 0,
      "ablated_degree": 0,
      "delta": 0
    },
    {
      "module": "bessel",
      "original_degree": 20,
      "ablated_degree": 19,
      "delta": -1
    },
    {
      "module": "dedekind_eta",
      "original_degree": 19,
      "ablated_degree": 18,
      "delta": -1
    },
    {
      "module": "exp",
      "original_degree": 5,
      "ablated_degree": 4,
      "delta": -1
    },
    {
      "module": "factorials",
      "original_degree": 22,
      "ablated_degree": 21,
      "delta": -1
    },
    {
      "module": "logic",
      "original_degree": 2,
      "ablated_degree": 1,
      "delta": -1
    },
    {
      "module": "weierstrass_elliptic",
      "original_degree": 13,
      "ablated_degree": 12,
      "delta": -1
    },
    {
      "module": "barnes_g",
      "original_degree": 2,
      "ablated_degree": 0,
      "delta": -2
    },
    {
      "module": "modular_transformations",
      "original_degree": 12,
      "ablated_degree": 10,
      "delta": -2
    },
    {
      "module": "sine",
      "original_degree": 4,
      "ablated_degree": 2,
      "delta": -2
    },
    {
      "module": "coulomb_wave",
      "original_degree": 13,
      "ablated_degree": 10,
      "delta": -3
    },
    {
      "module": "dirichlet",
      "original_degree": 18,
      "ablated_degree": 15,
      "delta": -3
    },
    {
      "module": "golden_ratio",
      "original_degree": 23,
      "ablated_degree": 20,
      "delta": -3
    },
    {
      "module": "imaginary_unit",
      "original_degree": 21,
      "ablated_degree": 18,
      "delta": -3
    },
    {
      "module": "sinc",
      "original_degree": 11,
      "ablated_degree": 8,
      "delta": -3
    },
    {
      "module": "sqrt",
      "original_degree": 18,
      "ablated_degree": 15,
      "delta": -3
    },
    {
      "module": "totient",
      "original_degree": 9,
      "ablated_degree": 6,
      "delta": -3
    },
    {
      "module": "carlson_elliptic",
      "original_degree": 27,
      "ablated_degree": 23,
      "delta": -4
    },
    {
      "module": "airy",
      "original_degree": 6,
      "ablated_degree": 1,
      "delta": -5
    },
    {
      "module": "const_gamma",
      "original_degree": 19,
      "ablated_degree": 14,
      "delta": -5
    },
    {
      "module": "digamma_function",
      "original_degree": 15,
      "ablated_degree": 10,
      "delta": -5
    },
    {
      "module": "bernoulli_numbers",
      "original_degree": 9,
      "ablated_degree": 2,
      "delta": -7
    },
    {
      "module": "agm",
      "original_degree": 21,
      "ablated_degree": 12,
      "delta": -9
    },
    {
      "module": "hurwitz_zeta",
      "original_degree": 16,
      "ablated_degree": 6,
      "delta": -10
    }
  ]
}