{
  "run_name": "null_gate_variant_a_seed42",
  "output_dir": "ergon\\pipeline_d\\runs\\null_gate_variant_a_seed42",
  "final_loss": 2.5006,
  "log_history": [
    {
      "loss": 2.707,
      "grad_norm": 0.7417641878128052,
      "learning_rate": 4.600000000000001e-05,
      "entropy": 2.632172155380249,
      "num_tokens": 290.0,
      "mean_token_accuracy": 0.45263158082962035,
      "epoch": 0.18518518518518517,
      "step": 5
    },
    {
      "loss": 2.6981,
      "grad_norm": 1.2301011085510254,
      "learning_rate": 4.1e-05,
      "entropy": 2.5957541942596434,
      "num_tokens": 580.0,
      "mean_token_accuracy": 0.4736842155456543,
      "epoch": 0.37037037037037035,
      "step": 10
    },
    {
      "loss": 2.5811,
      "grad_norm": 1.2812758684158325,
      "learning_rate": 3.6e-05,
      "entropy": 2.6229264736175537,
      "num_tokens": 872.0,
      "mean_token_accuracy": 0.4947368443012238,
      "epoch": 0.5555555555555556,
      "step": 15
    },
    {
      "loss": 2.5843,
      "grad_norm": 1.8038957118988037,
      "learning_rate": 3.1e-05,
      "entropy": 2.580331802368164,
      "num_tokens": 1163.0,
      "mean_token_accuracy": 0.5142165780067444,
      "epoch": 0.7407407407407407,
      "step": 20
    },
    {
      "loss": 2.5157,
      "grad_norm": 2.253121852874756,
      "learning_rate": 2.6000000000000002e-05,
      "entropy": 2.4723579406738283,
      "num_tokens": 1454.0,
      "mean_token_accuracy": 0.517483365535736,
      "epoch": 0.9259259259259259,
      "step": 25
    },
    {
      "loss": 2.5897,
      "grad_norm": 1.9780465364456177,
      "learning_rate": 2.1e-05,
      "entropy": 2.528401327133179,
      "num_tokens": 1744.0,
      "mean_token_accuracy": 0.4631579041481018,
      "epoch": 1.1111111111111112,
      "step": 30
    },
    {
      "loss": 2.506,
      "grad_norm": 1.4419500827789307,
      "learning_rate": 1.6000000000000003e-05,
      "entropy": 2.480750846862793,
      "num_tokens": 2034.0,
      "mean_token_accuracy": 0.5157894790172577,
      "epoch": 1.2962962962962963,
      "step": 35
    },
    {
      "loss": 2.5581,
      "grad_norm": 2.0889902114868164,
      "learning_rate": 1.1000000000000001e-05,
      "entropy": 2.541977787017822,
      "num_tokens": 2325.0,
      "mean_token_accuracy": 0.48257713913917544,
      "epoch": 1.4814814814814814,
      "step": 40
    },
    {
      "loss": 2.4274,
      "grad_norm": 1.549551248550415,
      "learning_rate": 6e-06,
      "entropy": 2.4953562736511232,
      "num_tokens": 2617.0,
      "mean_token_accuracy": 0.5332728326320648,
      "epoch": 1.6666666666666665,
      "step": 45
    },
    {
      "loss": 2.5006,
      "grad_norm": 1.4536679983139038,
      "learning_rate": 1.0000000000000002e-06,
      "entropy": 2.468763828277588,
      "num_tokens": 2907.0,
      "mean_token_accuracy": 0.5192982435226441,
      "epoch": 1.8518518518518519,
      "step": 50
    },
    {
      "train_runtime": 11.1018,
      "train_samples_per_second": 4.504,
      "train_steps_per_second": 4.504,
      "total_flos": 22873964571648.0,
      "train_loss": 2.566792621612549,
      "epoch": 1.8518518518518519,
      "step": 50
    }
  ],
  "trained_steps": 50,
  "saved_lora_path": "ergon\\pipeline_d\\runs\\null_gate_variant_a_seed42"
}